burstylimiter/__init__.py
burstylimiter/ratelimit.py
burstylimiter-0.1.1.dist-info/LICENSE
burstylimiter-0.1.1.dist-info/METADATA
burstylimiter-0.1.1.dist-info/WHEEL
burstylimiter-0.1.1.dist-info/RECORD
