Metadata-Version: 2.3
Name: burstylimiter
Version: 0.1.1
Summary: A Bursty Ratelimiter for Python. It allows two Limiters with different rates to be combined. Started as a limiter for my SpaceTradersAPI client.
License: GNU AFFERO GENERAL PUBLIC LICENSE
Keywords: ratelimiter,burstylimiter,ratelimiting,burstylimiting,ratelimit,rate,bursty,limiter,burstyrate,burstylimit
Author: Felix Baumkötter (feba66)
Author-email: feba66@web.de
Requires-Python: >=3.10
Classifier: License :: OSI Approved :: GNU Affero General Public License v3
Classifier: License :: Other/Proprietary License
Classifier: Programming Language :: Python :: 3
Classifier: Programming Language :: Python :: 3.10
Classifier: Programming Language :: Python :: 3.11
Classifier: Programming Language :: Python :: 3.12
Classifier: Programming Language :: Python :: 3.13
Project-URL: Issues, https://github.com/feba66/BurstyLimiter/issues
Project-URL: Repository, https://github.com/feba66/BurstyLimiter
